{".class": "MypyFile", "_fullname": "PyExcercize_page_165", "is_partial_stub_package": false, "is_stub": false, "names": {".class": "SymbolTable", "__doc__": {".class": "SymbolTableNode", "kind": "Gdef", "node": {".class": "Var", "flags": [], "fullname": "PyExcercize_page_165.__doc__", "name": "__doc__", "type": "builtins.str"}}, "__file__": {".class": "SymbolTableNode", "kind": "Gdef", "node": {".class": "Var", "flags": [], "fullname": "PyExcercize_page_165.__file__", "name": "__file__", "type": "builtins.str"}}, "__name__": {".class": "SymbolTableNode", "kind": "Gdef", "node": {".class": "Var", "flags": [], "fullname": "PyExcercize_page_165.__name__", "name": "__name__", "type": "builtins.str"}}, "__package__": {".class": "SymbolTableNode", "kind": "Gdef", "node": {".class": "Var", "flags": [], "fullname": "PyExcercize_page_165.__package__", "name": "__package__", "type": "builtins.str"}}, "barviha": {".class": "SymbolTableNode", "kind": "Gdef", "node": {".class": "Var", "flags": [], "fullname": "PyExcercize_page_165.barviha", "name": "barviha", "type": "PyExcercize_page_165.restaurant"}}, "hp": {".class": "SymbolTableNode", "kind": "Gdef", "node": {".class": "Var", "flags": [], "fullname": "PyExcercize_page_165.hp", "name": "hp", "type": "PyExcercize_page_165.restaurant"}}, "lounger": {".class": "SymbolTableNode", "kind": "Gdef", "node": {".class": "Var", "flags": [], "fullname": "PyExcercize_page_165.lounger", "name": "lounger", "type": "PyExcercize_page_165.restaurant"}}, "restaurant": {".class": "SymbolTableNode", "kind": "Gdef", "node": {".class": "TypeInfo", "_promote": null, "abstract_attributes": [], "bases": ["builtins.object"], "declared_metaclass": null, "defn": {".class": "ClassDef", "fullname": "PyExcercize_page_165.restaurant", "name": "restaurant", "type_vars": []}, "flags": [], "fullname": "PyExcercize_page_165.restaurant", "metaclass_type": null, "metadata": {}, "module_name": "PyExcercize_page_165", "mro": ["PyExcercize_page_165.restaurant", "builtins.object"], "names": {".class": "SymbolTable", "__init__": {".class": "SymbolTableNode", "kind": "Mdef", "node": {".class": "FuncDef", "arg_kinds": [0, 0, 0], "arg_names": ["self", "restaurant_name", "cuisine_type"], "flags": [], "fullname": "PyExcercize_page_165.restaurant.__init__", "name": "__init__", "type": null}}, "cuisine_type": {".class": "SymbolTableNode", "implicit": true, "kind": "Mdef", "node": {".class": "Var", "flags": [], "fullname": "PyExcercize_page_165.restaurant.cuisine_type", "name": "cuisine_type", "type": {".class": "AnyType", "missing_import_name": null, "source_any": null, "type_of_any": 1}}}, "describe_restaurant": {".class": "SymbolTableNode", "kind": "Mdef", "node": {".class": "FuncDef", "arg_kinds": [0], "arg_names": ["self"], "flags": [], "fullname": "PyExcercize_page_165.restaurant.describe_restaurant", "name": "describe_restaurant", "type": null}}, "open_restaurant": {".class": "SymbolTableNode", "kind": "Mdef", "node": {".class": "FuncDef", "arg_kinds": [0], "arg_names": ["self"], "flags": [], "fullname": "PyExcercize_page_165.restaurant.open_restaurant", "name": "open_restaurant", "type": null}}, "restaurant_name": {".class": "SymbolTableNode", "implicit": true, "kind": "Mdef", "node": {".class": "Var", "flags": [], "fullname": "PyExcercize_page_165.restaurant.restaurant_name", "name": "restaurant_name", "type": {".class": "AnyType", "missing_import_name": null, "source_any": null, "type_of_any": 1}}}}, "tuple_type": null, "type_vars": [], "typeddict_type": null}}, "user": {".class": "SymbolTableNode", "kind": "Gdef", "node": {".class": "TypeInfo", "_promote": null, "abstract_attributes": [], "bases": ["builtins.object"], "declared_metaclass": null, "defn": {".class": "ClassDef", "fullname": "PyExcercize_page_165.user", "name": "user", "type_vars": []}, "flags": [], "fullname": "PyExcercize_page_165.user", "metaclass_type": null, "metadata": {}, "module_name": "PyExcercize_page_165", "mro": ["PyExcercize_page_165.user", "builtins.object"], "names": {".class": "SymbolTable", "__init__": {".class": "SymbolTableNode", "kind": "Mdef", "node": {".class": "FuncDef", "arg_kinds": [0, 0, 0, 4], "arg_names": ["self", "first_name", "last_name", "user_info"], "flags": [], "fullname": "PyExcercize_page_165.user.__init__", "name": "__init__", "type": null}}, "describe_user": {".class": "SymbolTableNode", "kind": "Mdef", "node": {".class": "FuncDef", "arg_kinds": [0], "arg_names": ["self"], "flags": [], "fullname": "PyExcercize_page_165.user.describe_user", "name": "describe_user", "type": null}}, "first_name": {".class": "SymbolTableNode", "implicit": true, "kind": "Mdef", "node": {".class": "Var", "flags": [], "fullname": "PyExcercize_page_165.user.first_name", "name": "first_name", "type": {".class": "AnyType", "missing_import_name": null, "source_any": null, "type_of_any": 1}}}, "greet_user": {".class": "SymbolTableNode", "kind": "Mdef", "node": {".class": "FuncDef", "arg_kinds": [0], "arg_names": ["self"], "flags": [], "fullname": "PyExcercize_page_165.user.greet_user", "name": "greet_user", "type": null}}, "last_name": {".class": "SymbolTableNode", "implicit": true, "kind": "Mdef", "node": {".class": "Var", "flags": [], "fullname": "PyExcercize_page_165.user.last_name", "name": "last_name", "type": {".class": "AnyType", "missing_import_name": null, "source_any": null, "type_of_any": 1}}}, "user_info": {".class": "SymbolTableNode", "implicit": true, "kind": "Mdef", "node": {".class": "Var", "flags": [], "fullname": "PyExcercize_page_165.user.user_info", "name": "user_info", "type": {".class": "AnyType", "missing_import_name": null, "source_any": null, "type_of_any": 1}}}}, "tuple_type": null, "type_vars": [], "typeddict_type": null}}, "user_1": {".class": "SymbolTableNode", "kind": "Gdef", "node": {".class": "Var", "flags": [], "fullname": "PyExcercize_page_165.user_1", "name": "user_1", "type": "PyExcercize_page_165.user"}}}, "path": "c:\\Users\\RomaMexanik\\Desktop\\Projects\\PythonStart\\Python_Chapter_9_Classes\\PyExcercize_page_165.py"}